{
  "id": "54632428290",
  "name": "Glockenweihe Walbertsweiler 1963 IV",
  "description": "",
  "count_views": "0",
  "count_faves": "0",
  "count_comments": "1",
  "date_taken": "2025-07-04 01:57:26",
  "count_tags": "4",
  "count_notes": "0",
  "rotation": 0,
  "date_imported": "2025-07-04 01:57:26",
  "photopage": "https://www.flickr.com/photos/199943033@N03/54632428290/",
  "original": "/files/images/glockenweihe-walbertsweiler-1963-iv_54632428290_o.jpg",
  "license": "All Rights Reserved",
  "geo": [],
  "groups": [],
  "albums": [
    {
      "id": "72177720327302992",
      "title": "150_Walbertsweiler",
      "url": "https://www.flickr.com/photos//albums/72177720327302992"
    }
  ],
  "tags": [
    {
      "tag": "Walbertsweiler",
      "user": "https://www.flickr.com/photos/199943033@N03/",
      "date_create": "2025-07-04 01:57:21"
    },
    {
      "tag": "kirche",
      "user": "https://www.flickr.com/photos/199943033@N03/",
      "date_create": "2025-07-04 01:57:21"
    },
    {
      "tag": "glockenweihe",
      "user": "https://www.flickr.com/photos/199943033@N03/",
      "date_create": "2025-07-04 01:57:21"
    },
    {
      "tag": "1963",
      "user": "https://www.flickr.com/photos/199943033@N03/",
      "date_create": "2025-07-04 01:57:21"
    }
  ],
  "people": [],
  "notes": [],
  "privacy": "private",
  "comment_permissions": "only you",
  "tagging_permissions": "only you",
  "safety": "safe",
  "comments": [
    {
      "id": "72157720445009181",
      "date": "2025-07-04 02:01:12",
      "user": "199943033@N03",
      "comment": "Foto von 1963 aus Archiv Gemeinde Wald\nKommentar von Stefanie Grüner",
      "url": "https://www.flickr.com/photos/199943033@N03/54632428290//#comment72157720445009181"
    }
  ],
  "preview": "/files/images/thumbnails/photo-54632428290-thumb.jpg"
}
