{
  "id": "54855340865",
  "name": "Punsch-Essenz Apotheker Albert Sautermeister",
  "description": "",
  "count_views": "0",
  "count_faves": "0",
  "count_comments": "1",
  "date_taken": "2025-10-14 12:20:20",
  "count_tags": "0",
  "count_notes": "0",
  "rotation": 0,
  "date_imported": "2025-10-14 12:20:20",
  "photopage": "https://www.flickr.com/photos/199943033@N03/54855340865/",
  "original": "/files/images/punsch-essenz-apotheker-albert-sautermeister_54855340865_o.jpg",
  "license": "All Rights Reserved",
  "geo": [],
  "groups": [],
  "albums": [
    {
      "id": "72177720329684208",
      "title": "202_Apotheker Sautermeister",
      "url": "https://www.flickr.com/photos//albums/72177720329684208"
    }
  ],
  "tags": [],
  "people": [],
  "notes": [],
  "privacy": "private",
  "comment_permissions": "only you",
  "tagging_permissions": "only you",
  "safety": "safe",
  "comments": [
    {
      "id": "72157720465312907",
      "date": "2025-10-14 12:23:17",
      "user": "199943033@N03",
      "comment": "Aus Ordner von Sandra Häusler \nApotheker Albert Sautermeister \nKommentar von Stefanie Grüner",
      "url": "https://www.flickr.com/photos/199943033@N03/54855340865//#comment72157720465312907"
    }
  ],
  "preview": "/files/images/thumbnails/photo-54855340865-thumb.jpg"
}
